CHANGELOG.md
MANIFEST.in
README.md
setup.py
docs/features.rst
docs/getting_started.rst
docs/index.rst
docs/module_cgi.rst
docs/module_html.rst
docs/module_server.rst
docs/module_web.rst
pyy/__init__.py
pyy.egg-info/PKG-INFO
pyy.egg-info/SOURCES.txt
pyy.egg-info/dependency_links.txt
pyy.egg-info/top_level.txt
pyy/html/__init__.py
pyy/html/document.py
pyy/html/dom1core.py
pyy/html/pyy_tag.py
pyy/html/tags.py
pyy/html/util.py
pyy/server/__init__.py
pyy/server/fileserver.py
pyy/server/http.py
pyy/server/httpserver.py
pyy/server/pyyserver.py
pyy/server/run.py
pyy/server/server.py
pyy/server/syntaxfileserver.py
pyy/server/threadio.py
pyy/server/threadserver.py
pyy/tests/__init__.py
pyy/tests/test.py
pyy/tests/html/__init__.py
pyy/tests/html/attributes.py
pyy/tests/html/rendering.py
pyy/tests/server/__init__.py
pyy/tests/web/__init__.py
pyy/tests/web/cookies.py
pyy/tests/web/resolvers.py
pyy/tests/web/test/__init__.py
pyy/tests/web/test/hi.py
pyy/tests/web/test/admin/__init__.py
pyy/tests/web/test/admin/a.py
pyy/web/__init__.py
pyy/web/cgi.py
pyy/web/cookie.py
pyy/web/httpmessage.py
pyy/web/page.py
pyy/web/parsers.py
pyy/web/routing.py
pyy/web/tornado_simple_server.py
pyy/web/url.py
pyy/web/wsgi.py
test/test_document.py
test/test_html.py
test/test_routing.py