Metadata-Version: 1.1
Name: pyy
Version: 1.1.16
Summary: Python library for creating (X)HTML pages with the use of objects.
Home-page: http://github.com/Knio/pyy/
Author: Tom Flanagan and Jake Wharton
Author-email: theknio@gmail.com
License: LICENSE.txt
Keywords: framework templating template html xhtml python html5
Platform: UNKNOWN
Classifier: Programming Language :: Python
Classifier: Operating System :: OS Independent
Classifier: Topic :: Software Development :: Libraries :: Application Frameworks
Classifier: Topic :: Internet :: WWW/HTTP :: Dynamic Content
Classifier: Intended Audience :: Developers
